parallel_sort.libs/libtbb-79d9bc54.so.2
parallel_sort-0.2.1.dist-info/top_level.txt
parallel_sort-0.2.1.dist-info/RECORD
parallel_sort-0.2.1.dist-info/LICENSE
parallel_sort-0.2.1.dist-info/METADATA
parallel_sort-0.2.1.dist-info/WHEEL
parallel_sort/__init__.py
parallel_sort/_version.py
parallel_sort/extension.cpython-311-x86_64-linux-gnu.so
parallel_sort/src/parallel_sort.pyx
parallel_sort/src/parallel_sort.cpp
parallel_sort/src/parallel_sort.hpp
