Metadata-Version: 2.1
Name: parallel-sort
Version: 0.2.1
Summary: Cython interface to parallel sorting routines
Author-email: Calvin Sykes <sykescalvin09@gmail.com>
License: MIT License
Project-URL: Repository, https://github.com/calvin-sykes/cython_parallel_sort.git
Classifier: Programming Language :: Python :: 3
Classifier: License :: OSI Approved :: MIT License
Classifier: Operating System :: POSIX :: Linux
Requires-Python: >=3.7
License-File: LICENSE
Requires-Dist: numpy
